flask_docs/__init__.py
flask_docs/version.py
flask_docs/assets/debugger.png
flask_docs/assets/sample_app_add.png
flask_docs/assets/sample_app_delete.png
flask_docs/assets/sample_app_get.png
flask_docs/assets/sample_app_restful_get.png
flask_docs/assets/sample_app_restful_post.png
flask_docs/static/css/element-ui-2.15.6.min.css
flask_docs/static/css/github-11.2.0.min.css
flask_docs/static/css/github-markdown-1.0.0.min.css
flask_docs/static/css/fonts/element-icons.ttf
flask_docs/static/css/fonts/element-icons.woff
flask_docs/static/icon/book.svg
flask_docs/static/js/FileSaver-2.0.5.min.js
flask_docs/static/js/axios-0.22.0.min.js
flask_docs/static/js/crypto-js-4.1.1.min.js
flask_docs/static/js/element-ui-2.15.6.min.js
flask_docs/static/js/highlight-11.2.0.min.js
flask_docs/static/js/marked-3.0.7.min.js
flask_docs/static/js/vue-2.6.14.min.js
flask_docs/static/js/vue-i18n-8.26.5.min.js
flask_docs/static/locale/zh.js
flask_docs/templates/css_template_cdn.html
flask_docs/templates/css_template_local.html
flask_docs/templates/index.html
flask_docs/templates/js_template_cdn.html
flask_docs/templates/js_template_local.html
Flask_Docs-0.7.6.dist-info/LICENSE
Flask_Docs-0.7.6.dist-info/METADATA
Flask_Docs-0.7.6.dist-info/WHEEL
Flask_Docs-0.7.6.dist-info/top_level.txt
Flask_Docs-0.7.6.dist-info/RECORD
