Metadata-Version: 2.1
Name: Flask-Docs
Version: 0.7.6
Summary: Adds Docs support to Flask.
Home-page: https://github.com/kwkwc/flask-docs
Author: kwkw
Author-email: 
License: MIT
Keywords: flask,api,apidoc,doc,docs,documentation,md,markdown,RESTful,auto
Platform: any
Classifier: Environment :: Web Environment
Classifier: Intended Audience :: Developers
Classifier: License :: OSI Approved :: MIT License
Classifier: Operating System :: OS Independent
Classifier: Programming Language :: Python
Classifier: Programming Language :: Python :: 3
Classifier: Topic :: Internet :: WWW/HTTP :: Dynamic Content
Classifier: Topic :: Software Development :: Libraries :: Python Modules
License-File: LICENSE
Requires-Dist: Flask
